mongodb_formatter
